n2v/__init__.py
n2v/_version.py
n2v/grider.py
n2v/inverter.py
n2v/timer.dat
n2v/data/README.md
n2v/data/grid.npy
n2v/data/vxc_be.npy
n2v/data/vxc_ne.npy
n2v/engines/__init__.py
n2v/engines/engine.py
n2v/engines/psi4.py
n2v/engines/pyscf.py
n2v/grid/__init__.py
n2v/grid/basis_set_artifact_correction.py
n2v/grid/grider.py
n2v/grid/psi4grider.py
n2v/grid/pyscfgrider.py
n2v/grid/__pycache__/grider.cpython-38.pyc.139656896967088
n2v/grid/__pycache__/grider.cpython-38.pyc.139894062592304
n2v/grid/__pycache__/grider.cpython-38.pyc.139936759078960
n2v/grid/__pycache__/grider.cpython-38.pyc.140203949085104
n2v/grid/__pycache__/grider.cpython-38.pyc.140269992954416
n2v/grid/__pycache__/grider.cpython-38.pyc.140310558903472
n2v/grid/__pycache__/grider.cpython-38.pyc.140355366850608
n2v/grid/__pycache__/grider.cpython-38.pyc.140414855282736
n2v/grid/__pycache__/grider.cpython-38.pyc.140415597547952
n2v/grid/__pycache__/grider.cpython-38.pyc.140598845386800
n2v/grid/__pycache__/grider.cpython-38.pyc.140673345683504
n2v/methods/direct.py
n2v/methods/mrks.py
n2v/methods/oucarter.py
n2v/methods/pdeco.py
n2v/methods/random.py
n2v/methods/wuyang.py
n2v/methods/zmp.py
n2v/methods/__pycache__/oucarter.cpython-38.pyc.139656896956576
n2v/methods/__pycache__/oucarter.cpython-38.pyc.139894062569920
n2v/methods/__pycache__/oucarter.cpython-38.pyc.140203949066688
n2v/methods/__pycache__/oucarter.cpython-38.pyc.140269992896096
n2v/methods/__pycache__/oucarter.cpython-38.pyc.140415597537440
n2v/methods/__pycache__/wuyang.cpython-38.pyc.139957296670736
n2v/methods/__pycache__/wuyang.cpython-38.pyc.140180912875968
n2v/methods/__pycache__/zmp.cpython-38.pyc.139633703402160
n2v/methods/__pycache__/zmp.cpython-38.pyc.139637373451184
n2v/methods/__pycache__/zmp.cpython-38.pyc.139656897469872
n2v/methods/__pycache__/zmp.cpython-38.pyc.139668140456880
n2v/methods/__pycache__/zmp.cpython-38.pyc.139693717322544
n2v/methods/__pycache__/zmp.cpython-38.pyc.139701271047216
ntov-0.5.0.dist-info/LICENSE
ntov-0.5.0.dist-info/METADATA
ntov-0.5.0.dist-info/WHEEL
ntov-0.5.0.dist-info/top_level.txt
ntov-0.5.0.dist-info/RECORD
