Metadata-Version: 2.1
Name: ntov
Version: 0.5.0
Summary: UNKNOWN
Home-page: UNKNOWN
Author: Wasserman Group
Author-email: gonza445@purdue.edu
License: BSD-3-Clause
Platform: UNKNOWN
Requires-Dist: numpy
Requires-Dist: opt-einsum
Requires-Dist: scipy
